dailyfresh/__init__.py
dailyfresh/utility.py
dailyfresh-0.0.2.dist-info/LICENSE
dailyfresh-0.0.2.dist-info/METADATA
dailyfresh-0.0.2.dist-info/WHEEL
dailyfresh-0.0.2.dist-info/top_level.txt
dailyfresh-0.0.2.dist-info/zip-safe
dailyfresh-0.0.2.dist-info/RECORD
