Metadata-Version: 2.1
Name: dailyfresh
Version: 0.0.2
Summary: dailyfresh: python tools for descriptive and comparitive effectiveness studies
Home-page: UNKNOWN
Author: Epic
License: Epic
Platform: UNKNOWN
Requires-Python: >3
Provides-Extra: all
Requires-Dist: autopep8 (>=1.3.5) ; extra == 'all'
Requires-Dist: mypy (>=0.761) ; extra == 'all'
Requires-Dist: pytest-cov (>=2.5.1) ; extra == 'all'
Requires-Dist: pytest-json (>=0.4.0) ; extra == 'all'
Requires-Dist: pytest (>=5.1.1) ; extra == 'all'
Requires-Dist: sphinx-rtd-theme (>=0.5.0) ; extra == 'all'
Requires-Dist: sphinx (>=3.3.1) ; extra == 'all'
Provides-Extra: dev
Requires-Dist: autopep8 (>=1.3.5) ; extra == 'dev'
Requires-Dist: mypy (>=0.761) ; extra == 'dev'
Requires-Dist: pytest-cov (>=2.5.1) ; extra == 'dev'
Requires-Dist: pytest-json (>=0.4.0) ; extra == 'dev'
Requires-Dist: pytest (>=5.1.1) ; extra == 'dev'
Provides-Extra: docs
Requires-Dist: sphinx-rtd-theme (>=0.5.0) ; extra == 'docs'
Requires-Dist: sphinx (>=3.3.1) ; extra == 'docs'
